{
    "title": "Defund the Police – Top 3 Pros and Cons",
    "introduction": [],
    "pros": [],
    "cons": [],
    "sources": [
        {
            "id": "",
            "title": "1. Clare Proctor and Juan Pablo Garnham, “For Those Texas Organizers and Officials, Defunding the Police Means Remedying Effects of Racism,” texastribune.org, June 13, 2020",
            "docid": 5047
        },
        {
            "id": "",
            "title": "2. Amanda Arnold, “What Exactly Does It Mean to Defund the Police?,” thecut.com, June 12, 2020",
            "docid": 5048
        },
        {
            "id": "",
            "title": "3. Annie Lowrey, “Defund the Police,” theatlantic.com, June 5, 2020",
            "docid": 5049
        },
        {
            "id": "",
            "title": "4. Melissa Gira Grant, “The Rush to Redefine ‘Defund the Police,” newrepublic.com, June 9, 2020",
            "docid": 5050
        },
        {
            "id": "",
            "title": "5. Scottie Andrew, “There’s a Growing Call to Defund Police. Here’s What It Means,” cnn.com, June 17, 2020",
            "docid": 5051
        },
        {
            "id": "",
            "title": "6. Ruairí Arrieta-Kenna, “The Deep Roots--and New Offshoots--of ‘Abolish the Police,’” politico.com, June 12, 2020",
            "docid": 5052
        },
        {
            "id": "",
            "title": "7. Urban Institute, “Police and Corrections Expenditures,” urban.org (accessed June 17, 2020)",
            "docid": 5053
        },
        {
            "id": "",
            "title": "8. Polly Mosendz and Jameelah D. Robinson, “While Crime Fell, the Cost of Cops Soared,” bloomberg.com, June 4, 2020",
            "docid": 5054
        },
        {
            "id": "",
            "title": "9. Richard C. Auxier, “What Police Spending Data Can (and Cannot) Explain amid Calls to Defund the Police,” urban.org, June 9, 2020",
            "docid": 5055
        },
        {
            "id": "",
            "title": "10. Kendall Karson, “64% of Americans Oppose 'Defund the Police' Movement, Key Goals: POLL.” abcnews.go.com, June 12, 2020",
            "docid": 5056
        },
        {
            "id": "",
            "title": "11. Paige Fernandez, “Defunding the Police Will Actually Make Us Safer,” aclu.org, June 11, 2020",
            "docid": 5057
        },
        {
            "id": "",
            "title": "12. ACLU, “Police Militarization,” aclu.org (accessed June 17, 2020)",
            "docid": 5058
        },
        {
            "id": "",
            "title": "13. mpd150, “Enough Is Enough: A 150 Year Performance Review of the Minneapolis Police Department,” mpd150.com, 2017",
            "docid": 5059
        },
        {
            "id": "",
            "title": "14. John Hagan, “Risk of Being Killed by Police Use of Force in the United States by Age, Race-Ethnicity, and Sex,” pnas.org, Aug. 20, 2019",
            "docid": 5060
        },
        {
            "id": "",
            "title": "15. Bureau of Justice Statistics, “Contacts between Police and the Public, 2015,” bjs.gov. Oct. 2018",
            "docid": 5061
        },
        {
            "id": "",
            "title": "16. Alexi Jones, “Police Stops Are Still Marred by Racial Discrimination, New Data Shows,” prisonpolicy.oeg, Oct. 12, 2018",
            "docid": 5062
        },
        {
            "id": "",
            "title": "17. Mapping Police Violence, “Police Violence Map,” mappingpoliceviolence.org (accessed June 17, 2020)",
            "docid": 5063
        },
        {
            "id": "",
            "title": "18. Sarah Beller, “The American Public Health Association Declares Police Violence a Public Health Issue,” filtermag.org, Nov. 15, 2018",
            "docid": 5064
        },
        {
            "id": "",
            "title": "19. Amina Khan, “In New York, Major Crime Complaints Fell when Cops Took a Break from ‘Proactive Policing,’” latimes.com, Sep. 25, 2017",
            "docid": 5065
        },
        {
            "id": "",
            "title": "20. Mariame Kaba, “Yes, We Mean Literally Abolish the Police,” nytimes.com, June 12, 2020",
            "docid": 5066
        },
        {
            "id": "",
            "title": "21. Marilynn S. Johnson,Street Justice: A History of Police Violence in New York City, 2004",
            "docid": 5067
        },
        {
            "id": "",
            "title": "22. Philip V. McHarris and Thenjiwe McHarris, “No More Money for the Police,” nytimes.com, May 30, 2020",
            "docid": 5068
        },
        {
            "id": "",
            "title": "23. Jeff Hargarten, et al., “Every Police-Involved Death in Minnesota since 2000,” startribune.com, May 31, 2020",
            "docid": 5069
        },
        {
            "id": "",
            "title": "24. Vera Bergengruen and Tessa Berenson, “'It Was a Tinderbox.' How George Floyd’s Killing Highlighted America's Police Reform Failures,” time.com, June 4, 2020",
            "docid": 5070
        },
        {
            "id": "",
            "title": "25. Sam Levin, “‘It’s Not about Bad Apples’: How US Police Reforms Have Failed to Stop Brutality and Violence,” theguardian.com, June 16, 2020",
            "docid": 5071
        },
        {
            "id": "",
            "title": "26. Kirsten Weir, “Policing in Black and White,” apa.org, Dec. 2016",
            "docid": 5072
        },
        {
            "id": "",
            "title": "27. Alex Vitale, “Why Police Reform Is Not Enough,” yesmagazine.org, June 2, 2020",
            "docid": 5073
        },
        {
            "id": "",
            "title": "27. Stuart Schrader, “Police Reform Won’t Fix a System That Was Built to Abuse Power,” thenation.com, June 12, 2020",
            "docid": 5074
        },
        {
            "id": "",
            "title": "29. Ursula Perano, “Black Lives Matter Co-Founder Explains ‘Defund the Police’ Slogan,” axios.com, June 7, 2020",
            "docid": 5075
        },
        {
            "id": "",
            "title": "30. Patrick Sharkey, “Why Do We Need the Police?,” washingtonpost.com, June 12, 2020",
            "docid": 5076
        },
        {
            "id": "",
            "title": "31. Village of Hillsdale Police Department, Job Ad, jeffco.edu, 2019",
            "docid": 5077
        },
        {
            "id": "",
            "title": "32. Parija Kavilanz, “Target Is Raising Its Minimum Wage to $15 an Hour in July,” cnn.com, June 17, 2020",
            "docid": 5078
        },
        {
            "id": "",
            "title": "33. In Plain Sight, “Police Pay Gap: Many of America’s Finest Struggle on Poverty Wages,” nbcnews.com, Oct 26, 2014",
            "docid": 5079
        },
        {
            "id": "",
            "title": "34. Simon Weichselbaum and Nicole Lewis, “Support for Defunding the Police Department Is Growing. Here’s Why It’s Not a Silver Bullet.,” themarshallproject.org, June 9, 2020",
            "docid": 5080
        },
        {
            "id": "",
            "title": "35. Vikram Dodd, “Police Cuts ‘Likely Contributed’ to Rise in Violent Crime, Leaked Report reveals,” theguardian.com, Apr. 8, 2018",
            "docid": 5081
        },
        {
            "id": "",
            "title": "36. Lizzie Dearden, “Police Cuts Contributed to Rise in Murders in Britain, Home Office Report Says,” independent.co.uk, Mar. 5, 2020",
            "docid": 5082
        },
        {
            "id": "",
            "title": "37. Police Executive Research Forum, “Is the Economic Downturn Fundamentally Changing How We Police?,” policeforum.org, Dec. 2010",
            "docid": 5083
        },
        {
            "id": "",
            "title": "38. C. Jarret Dieterle, “Citation Nation,” city-journal.org, Apr. 4, 2017",
            "docid": 5084
        },
        {
            "id": "",
            "title": "39. Chris Megerian, “Disband the Police? Camden Already Did That,” latimes.com, June 10, 2020",
            "docid": 5085
        },
        {
            "id": "",
            "title": "40. FBI, “2018 Crime in the United States,” ucr.fbi.gov (accessed June 18, 2020)",
            "docid": 5086
        },
        {
            "id": "",
            "title": "41. Emily Bazelon, “A Discussion about How to reform Policing.,” nytimes.com, June 13, 2020",
            "docid": 5087
        },
        {
            "id": "",
            "title": "42. George Fachner and Steven Carter, “Collaborative Reform Initiative: An Assessment of Deadly Force in the Philadelphia Police Department,” phillypolice.com, 2015",
            "docid": 5088
        },
        {
            "id": "",
            "title": "43. Chris Kahn, “Exclusive: Most Americans, Including Republicans, Support Sweeping Democratic Police Reform Proposals - Reuters/Ipsos Poll,” reuters.com, June 11, 2020",
            "docid": 5089
        },
        {
            "id": "",
            "title": "44. Jill Leovy, “The Underpolicing of Black America,” wsj.com, Jan. 23, 2015",
            "docid": 5090
        },
        {
            "id": "",
            "title": "45. Tom Schuba, Sam Charles, and Matthew Hendrickson, “18 Murders in 24 Hours: Inside the Most Violent Day in 60 Years in Chicago,” chicago.suntimes.com, June 8, 2020",
            "docid": 5091
        },
        {
            "id": "",
            "title": "46. President’s Task Force on 21st Century Policing, “Final Report of the President’s Task Force on 21st Century Policing,” cops.usdoj.gov, 2015",
            "docid": 5092
        },
        {
            "id": "",
            "title": "47. Charles Ramsey and Laurie O. Robinson, “Adopt Minimum National Police Use-of-Force Standards and Train Cops for Interaction,” usatoday.com, May 29, 2020",
            "docid": 5093
        },
        {
            "id": "",
            "title": "48. Equal Justice Initiative, “Reforming Policing in America 2020,” eji.org, 2020",
            "docid": 5094
        },
        {
            "id": "",
            "title": "49. Ed Pilkington, “‘State-Sanctioned Violence’: US Police Fail to Meet Basic Human Rights Standards,” theguardian.com, June 22, 2020",
            "docid": 5095
        },
        {
            "id": "",
            "title": "50. University of Chicago Law School - International Human Rights Clinic, \"Deadly Discretion: The Failure of Police Use of Force Policies to Meet Fundamental International Human Rights Law and Standards,” chicagounbound.uchicago.edu, 2020",
            "docid": 5096
        },
        {
            "id": "",
            "title": "51. Jamiles Lartey, “By the Numbers: US Police Kill More in Days than Other Countries Do in Years,” theguardian.com, June 9, 2015",
            "docid": 5097
        },
        {
            "id": "",
            "title": "52. Miriam Berger and Rick Noack, “From Guns to Neck Restraint: How Police Tactics Differ around the World,” washingtonpost.com, June 6, 2020",
            "docid": 5098
        },
        {
            "id": "",
            "title": "53. Jonathan Martin, Alexander Burns, and Thomas Kaplan, “Biden Walks a Cautious Line as He Opposes Defunding the Police,” nytimes.com, June 8, 2020",
            "docid": 5099
        },
        {
            "id": "",
            "title": "54. Brett Samuels, “Trump: There Won’t Be Any Defunding of Police,” thehill.com, June 8, 2020",
            "docid": 5100
        },
        {
            "id": "",
            "title": "55. Andrew Marantz, “Bernie Sanders Is Not Done Fighting,” newyorker.com, June 9, 2020",
            "docid": 5101
        },
        {
            "id": "",
            "title": "56. Howie Hawkins, Twitter.com, June 12, 2020",
            "docid": 5102
        },
        {
            "id": "",
            "title": "57. For a World without Police, “The Problem,” aworldwithoutpolice.org (accessed June 18, 2020)",
            "docid": 5103
        },
        {
            "id": "",
            "title": "58. Kim Parker and Kiley Hurst, \"Growing Share of Americans Say They Want More Spending on Police in Their Area,\" pewresearch.org, Oct. 26, 2021",
            "docid": 5104
        },
        {
            "id": "",
            "title": "59. Ian T. Adams, Scott M. Mourtgos, and Justin Nix, \"Turnover in Large US Police Agencies Following the George Floyd Protests,\" osf.io/r9mjf/, Mar. 1, 2023",
            "docid": 5105
        },
        {
            "id": "",
            "title": "60. Martin Kaste, \"Police Didn’t Get Defunded but Many Large Departments Are Shrinking,\" npr.org, Mar. 18, 2023",
            "docid": 5106
        },
        {
            "id": "",
            "title": "61. The Urban Institute, \"Criminal Justice Expenditures: Police, Corrections, and Courts,\" urban.org (accessed July 6, 2023)",
            "docid": 5107
        },
        {
            "id": "",
            "title": "62. Charles M. Blow, \"‘Defund the Police’ Is Dead. Now What?,\" nytimes.com, Aug. 31, 2022",
            "docid": 5108
        },
        {
            "id": "",
            "title": "63. Lauren M. Johnson, \"Colin Kaepernick Calls for Abolishing Police and Prisons in New Essay Series,\" cnn.com, Oct. 10, 2020",
            "docid": 5109
        },
        {
            "id": "",
            "title": "64. Will Saletan, \"Americans Don’t Want to Defund the Police. Here’s What They Do Want.,\" slate.com, Oct. 17, 2021",
            "docid": 5110
        },
        {
            "id": "",
            "title": "65. Chris Cillizza, \"This Was the Single Most Revealing Line in Biden’s State of the Union Speech,\" cnn.com, Mar. 2, 2022",
            "docid": 5111
        }
    ],
    "discussion": [
        "1. Should police departments be defunded? Why or why not?",
        "2. Are any police reform efforts helpful? Which reforms? Explain your answers.",
        "3. Do you think abolishing police departments would resolve or create more problems for communities of color? Explain your answer.",
        "4. Do you think defunding or eliminating police departments would lead togreaterviolence in our cities?  Explain your answer."
    ],
    "action": [
        "1. Explore the resources provided byMovement for Black Lives(M4BL), which promotes defunding the police.",
        "2. Examine which states have and have not enacted police reform laws since May 25, 2020 with theNational Conference of State Legislatures.",
        "3. Consider the con position of Black former police officer,Erroll G. Southers.",
        "4. Consider how you felt about the issue before reading this article. After reading the pros and cons on this topic, has your thinking changed? If so, how? List two to three ways. If your thoughts have not changed, list two to three ways your better understanding of the “other side of the issue” now helps you better argue your position.",
        "5. Push for the position and policies you support by writing US nationalsenatorsandrepresentatives."
    ],
    "url": "https://www.procon.org/headlines/defund-the-police-top-3-pros-and-cons/"
}